{"session_id": "1476a132-9b39-4dff-8abc-c257ec6b744b", "job_id": "82ceb176-f078-4068-b2f3-70ec6becd97f", "status": "succeeded", "audio_url": "https://mymedicalapp.loca.lt/files/1476a132-9b39-4dff-8abc-c257ec6b744b.wav", "filename": "medical_note_3.wav", "result": {"diarization": [{"speaker": "SPEAKER_01", "start": 2.425, "end": 4.885}, {"speaker": "SPEAKER_01", "start": 5.965, "end": 7.165}, {"speaker": "SPEAKER_01", "start": 7.905, "end": 9.105}, {"speaker": "SPEAKER_01", "start": 10.545, "end": 19.185}, {"speaker": "SPEAKER_00", "start": 21.025, "end": 26.305}, {"speaker": "SPEAKER_00", "start": 26.445, "end": 26.525}, {"speaker": "SPEAKER_00", "start": 26.565, "end": 28.925}, {"speaker": "SPEAKER_00", "start": 33.605, "end": 38.285}, {"speaker": "SPEAKER_00", "start": 40.465, "end": 43.545}, {"speaker": "SPEAKER_00", "start": 43.785, "end": 46.725}], "transcript": [{"speaker": "Speaker 01", "text": "Hello, Namaste Dr. Saab So, I feel a lot of weakness I feel more tired I feel that my blood sugar has increased", "start": 2.425, "end": 18.59062570281147}, {"speaker": "Speaker 00", "text": "and it's a lot of pressure and it's a lot of pressure and it's a lot of pressure so let me suggest something I checked my recent blood show it's about 12 years ago so what will I suggest?", "start": 21.025, "end": 45.990625702811464}]}}